Workbook
Name TotalMonthlyExpenses: jan!$C$6
Name TotalMonthlyIncome: jan!$C$4
Name TotalMonthlySavings: jan!$C$8

Sheet jan
B1: Personal budget
B2: Percentage of income spent | C2: Summary
C3: TOTAL MONTHLY INCOME
C4: =SUM(MonthlyIncome[[#All],[AMOUNT]]) -> 2000
C5: TOTAL MONTHLY EXPENSES
C6: =SUM(MonthlyExpenses[AMOUNT])+SUM(Table6[])+SUM(Savings3[AMOUNT]) -> 400
C7: TOTAL MONTHLY SAVINGS
C8: =SUM(Savings3[AMOUNT]) -> 200
C9: CASH BALANCE
C10: =TotalMonthlyIncome-TotalMonthlyExpenses -> 1600
B12: Monthly income | H12: Monthly expenses | M12: Monthly savings
B13: ITEM | C13: AMOUNT | H13: ITEM | I13: DUE DATE | J13: AMOUNT | M13: DATE | N13: AMOUNT
B14: Income source 1 | C14: 0 | H14: Rent/mortgage | I14: 45658 | J14: 0 | M14: Date | N14: 0
B15: Income source 2 | C15: 2000 | H15: Electric | I15: [Date] | J15: 0 | M15: Date | N15: 200
B16: Other | C16: 0 | H16: Gas | I16: [Date] | J16: 0 | M16: Date | N16: 0
H17: Cell phone | I17: [Date] | J17: 0
H18: Groceries | I18: [Date] | J18: 100
H19: Auto expenses | I19: [Date] | J19: 0
H20: Investments | I20: [Date] | J20: 0
H21: Credit cards | I21: [Date] | J21: 0
B22: Monthly GYM expenses | H22: Personal care | I22: [Date] | J22: 0
B23: ITEM | C23: AMOUNT | H23: Food | I23: [Date] | J23: 0
B24: Banana | C24: 100 | H24: Miscellaneous | I24: [Date] | J24: 0
B25: Peanut butter
B26: Honey | C26: 0
B27: Oats | C27: 0
B28: Dates
B29: Chiceken / Panner
B30: Whey protien
B31: Creatin
B32: Nuts

Sheet feb
B1: Personal budget
B2: Percentage of income spent | C2: Summary
C3: TOTAL MONTHLY INCOME
C4: =SUM(MonthlyIncome5[[#All],[AMOUNT]]) -> 2000
C5: TOTAL MONTHLY EXPENSES
C6: =SUM(C8)+SUM(MonthlyExpenses6[AMOUNT])+SUM(Table69[AMOUNT]) -> 400
C7: TOTAL MONTHLY SAVINGS
C8: =SUM(Savings38[AMOUNT]) -> 200
C9: CASH BALANCE
C10: =C4-C6 -> 1600
B12: Monthly income | H12: Monthly expenses | M12: Monthly savings
B13: ITEM | C13: AMOUNT | H13: ITEM | I13: DUE DATE | J13: AMOUNT | M13: DATE | N13: AMOUNT
B14: Income source 1 | C14: 0 | H14: Rent/mortgage | I14: 45658 | J14: 0 | M14: Date | N14: 0
B15: Income source 2 | C15: 2000 | H15: Electric | I15: [Date] | J15: 0 | M15: Date | N15: 200
B16: Other | C16: 0 | H16: Gas | I16: [Date] | J16: 0 | M16: Date | N16: 0
H17: Cell phone | I17: [Date] | J17: 0
H18: Groceries | I18: [Date] | J18: 100
H19: Auto expenses | I19: [Date] | J19: 0
H20: Investments | I20: [Date] | J20: 0
H21: Credit cards | I21: [Date] | J21: 0
B22: Monthly GYM expenses | H22: Personal care | I22: [Date] | J22: 0
B23: ITEM | C23: AMOUNT | H23: Food | I23: [Date] | J23: 0
B24: Banana | H24: Miscellaneous | I24: [Date] | J24: 0
B25: Peanut butter | C25: 100 | J25: 0
B26: Honey | C26: 0
B27: Oats | C27: 0
B28: Dates
B29: Chiceken / Panner
B30: Whey protien
B31: Creatin
B32: Nuts

Sheet mar
B1: Personal budget
B2: Percentage of income spent | C2: Summary
C3: TOTAL MONTHLY INCOME
C4: =SUM(MonthlyIncome530[[#All],[AMOUNT]]) -> 2200
C5: TOTAL MONTHLY EXPENSES
C6: =SUM(MonthlyExpenses631[AMOUNT])+SUM(Table6933[AMOUNT])+SUM(Savings3832[AMOUNT]) -> 500
C7: TOTAL MONTHLY SAVINGS
C8: =SUM(Savings3832[AMOUNT]) -> 200
C9: CASH BALANCE
C10: =C4-C6 -> 1700
B12: Monthly income | H12: Monthly expenses | M12: Monthly savings
B13: ITEM | C13: AMOUNT | H13: ITEM | I13: DUE DATE | J13: AMOUNT | M13: DATE | N13: AMOUNT
B14: Income source 1 | C14: 200 | H14: Rent/mortgage | I14: 45658 | J14: 0 | M14: Date | N14: 0
B15: Income source 2 | C15: 2000 | H15: Electric | I15: [Date] | J15: 0 | M15: Date | N15: 200
B16: Other | H16: Gas | I16: [Date] | J16: 0 | M16: Date | N16: 0
H17: Cell phone | I17: [Date] | J17: 0
H18: Groceries | I18: [Date] | J18: 100
H19: Auto expenses | I19: [Date] | J19: 0
H20: Investments | I20: [Date] | J20: 100
H21: Credit cards | I21: [Date] | J21: 0
B22: Monthly GYM expenses | H22: Personal care | I22: [Date] | J22: 0
B23: ITEM | C23: AMOUNT | H23: Food | I23: [Date] | J23: 0
B24: Banana | C24: 100 | H24: Miscellaneous | I24: [Date] | J24: 0
B25: Peanut butter
B26: Honey | C26: 0
B27: Oats | C27: 0
B28: Dates
B29: Chiceken / Panner
B30: Whey protien
B31: Creatin
B32: Nuts

Sheet apr
B1: Personal budget
B2: Percentage of income spent | C2: Summary
C3: TOTAL MONTHLY INCOME
C4: =SUM(MonthlyIncome534[AMOUNT]) -> 2100
C5: TOTAL MONTHLY EXPENSES
C6: =SUM(MonthlyExpenses635[AMOUNT])+SUM(Table6937[AMOUNT])+SUM(Savings3836[AMOUNT]) -> 200
C7: TOTAL MONTHLY SAVINGS
C8: =SUM(Savings3836[AMOUNT]) -> 100
C9: CASH BALANCE
C10: =C4-C6 -> 1900
B12: Monthly income | H12: Monthly expenses | M12: Monthly savings
B13: ITEM | C13: AMOUNT | H13: ITEM | I13: DUE DATE | J13: AMOUNT | M13: DATE | N13: AMOUNT
B14: Income source 1 | C14: 0 | H14: Rent/mortgage | I14: 45658 | J14: 0 | M14: Date | N14: 0
B15: Income source 2 | C15: 2000 | H15: Electric | I15: [Date] | J15: 0 | M15: Date | N15: 0
B16: Other | C16: 100 | H16: Gas | I16: [Date] | J16: 0 | M16: Date | N16: 100
H17: Cell phone | I17: [Date] | J17: 0
H18: Groceries | I18: [Date] | J18: 0
H19: Auto expenses | I19: [Date] | J19: 0
H20: Investments | I20: [Date] | J20: 0
H21: Credit cards | I21: [Date] | J21: 0
B22: Monthly GYM expenses | H22: Personal care | I22: [Date] | J22: 0
B23: ITEM | C23: AMOUNT | H23: Food | I23: [Date] | J23: 0
B24: Banana | C24: 100 | H24: Miscellaneous | I24: [Date] | J24: 0
B25: Peanut butter | C25: 0
B26: Honey | C26: 0
B27: Oats | C27: 0
B28: Dates | C28: 0
B29: Chiceken / Panner
B30: Whey protien
B31: Creatin
B32: Nuts

Sheet may
B1: Personal budget
B2: Percentage of income spent | C2: Summary
C3: TOTAL MONTHLY INCOME
C4: =SUM(MonthlyIncome538[AMOUNT]) -> 2500
C5: TOTAL MONTHLY EXPENSES
C6: =SUM(MonthlyExpenses639[AMOUNT])+SUM(Table6941[AMOUNT])+SUM(Savings3840[AMOUNT]) -> 500
C7: TOTAL MONTHLY SAVINGS
C8: =SUM(Savings3840[AMOUNT]) -> 300
C9: CASH BALANCE
C10: =C4-C6 -> 2000
B12: Monthly income | H12: Monthly expenses | M12: Monthly savings
B13: ITEM | C13: AMOUNT | H13: ITEM | I13: DUE DATE | J13: AMOUNT | M13: DATE | N13: AMOUNT
B14: Income source 1 | C14: 400 | H14: Rent/mortgage | I14: 45658 | J14: 0 | M14: Date | N14: 0
B15: Income source 2 | C15: 2000 | H15: Electric | I15: [Date] | J15: 0 | M15: Date | N15: 200
B16: Other | C16: 100 | H16: Gas | I16: [Date] | J16: 100 | M16: Date | N16: 100
H17: Cell phone | I17: [Date] | J17: 0
H18: Groceries | I18: [Date] | J18: 0
H19: Auto expenses | I19: [Date] | J19: 0
H20: Investments | I20: [Date] | J20: 0
H21: Credit cards | I21: [Date] | J21: 0
B22: Monthly GYM expenses | H22: Personal care | I22: [Date] | J22: 0
B23: ITEM | C23: AMOUNT | H23: Food | I23: [Date] | J23: 0
B24: Banana | H24: Miscellaneous | I24: [Date] | J24: 0
B25: Peanut butter | J25: 0
B26: Honey | C26: 0
B27: Oats | C27: 100
B28: Dates
B29: Chiceken / Panner
B30: Whey protien
B31: Creatin
B32: Nuts

Sheet jun
B1: Personal budget
B2: Percentage of income spent | C2: Summary
C3: TOTAL MONTHLY INCOME
C4: =SUM(MonthlyIncome542[[#All],[AMOUNT]]) -> 3000
C5: TOTAL MONTHLY EXPENSES
C6: =SUM(MonthlyExpenses643[AMOUNT])+SUM(Table6945[AMOUNT])+SUM(Savings3844[AMOUNT]) -> 800
C7: TOTAL MONTHLY SAVINGS
C8: =SUM(Savings3844[AMOUNT]) -> 200
C9: CASH BALANCE
C10: =C4-C6 -> 2200
B12: Monthly income | H12: Monthly expenses | M12: Monthly savings
B13: ITEM | C13: AMOUNT | H13: ITEM | I13: DUE DATE | J13: AMOUNT | M13: DATE | N13: AMOUNT
B14: Income source 1 | C14: 500 | H14: Rent/mortgage | I14: 45658 | J14: 0 | M14: Date | N14: 0
B15: Income source 2 | C15: 2000 | H15: Electric | I15: [Date] | J15: 0 | M15: Date | N15: 200
B16: Other | C16: 500 | H16: Gas | I16: [Date] | J16: 0 | M16: Date | N16: 0
H17: Cell phone | I17: [Date] | J17: 0
H18: Groceries | I18: [Date] | J18: 0
H19: Auto expenses | I19: [Date] | J19: 0
H20: Investments | I20: [Date] | J20: 0
H21: Credit cards | I21: [Date] | J21: 0
B22: Monthly GYM expenses | H22: Personal care | I22: [Date] | J22: 500
B23: ITEM | C23: AMOUNT | H23: Food | I23: [Date] | J23: 0
B24: Banana | H24: Miscellaneous | I24: [Date] | J24: 0
B25: Peanut butter
B26: Honey | C26: 0
B27: Oats | C27: 100
B28: Dates
B29: Chiceken / Panner
B30: Whey protien
B31: Creatin
B32: Nuts

Sheet jul
B1: Personal budget
B2: Percentage of income spent | C2: Summary
C3: TOTAL MONTHLY INCOME
C4: =SUM(MonthlyIncome546[[#All],[AMOUNT]]) -> 3200
C5: TOTAL MONTHLY EXPENSES
C6: =SUM(MonthlyExpenses647[AMOUNT])+SUM(Table6949[AMOUNT])+SUM(Savings3848[AMOUNT]) -> 300
C7: TOTAL MONTHLY SAVINGS
C8: =SUM(Savings3848[AMOUNT]) -> 200
C9: CASH BALANCE
C10: =C4-C6 -> 2900
B12: Monthly income | H12: Monthly expenses | M12: Monthly savings
B13: ITEM | C13: AMOUNT | H13: ITEM | I13: DUE DATE | J13: AMOUNT | M13: DATE | N13: AMOUNT
B14: Income source 1 | C14: 400 | H14: Rent/mortgage | I14: 45658 | J14: 0 | M14: Date | N14: 0
B15: Income source 2 | C15: 2000 | H15: Electric | I15: [Date] | J15: 0 | M15: Date | N15: 200
B16: Other | C16: 800 | H16: Gas | I16: [Date] | J16: 0 | M16: Date | N16: 0
H17: Cell phone | I17: [Date] | J17: 0
H18: Groceries | I18: [Date] | J18: 0
H19: Auto expenses | I19: [Date] | J19: 0
H20: Investments | I20: [Date] | J20: 0
H21: Credit cards | I21: [Date] | J21: 0
B22: Monthly GYM expenses | H22: Personal care | I22: [Date] | J22: 0
B23: ITEM | C23: AMOUNT | H23: Food | I23: [Date] | J23: 0
B24: Banana | H24: Miscellaneous | I24: [Date] | J24: 0
B25: Peanut butter
B26: Honey | C26: 0
B27: Oats | C27: 100
B28: Dates
B29: Chiceken / Panner
B30: Whey protien
B31: Creatin
B32: Nuts

Sheet aug
B1: Personal budget
B2: Percentage of income spent | C2: Summary
C3: TOTAL MONTHLY INCOME
C4: =SUM(MonthlyIncome554[[#All],[AMOUNT]]) -> 3000
C5: TOTAL MONTHLY EXPENSES
C6: =SUM(MonthlyExpenses655[AMOUNT])+SUM(Table6957[AMOUNT])+SUM(Savings3856[AMOUNT]) -> 200
C7: TOTAL MONTHLY SAVINGS
C8: =SUM(Savings3856[AMOUNT]) -> 100
C9: CASH BALANCE
C10: =C4-C6 -> 2800
B12: Monthly income | H12: Monthly expenses | M12: Monthly savings
B13: ITEM | C13: AMOUNT | H13: ITEM | I13: DUE DATE | J13: AMOUNT | M13: DATE | N13: AMOUNT
B14: Income source 1 | C14: 400 | H14: Rent/mortgage | I14: 45658 | J14: 0 | M14: Date | N14: 0
B15: Income source 2 | C15: 2000 | H15: Electric | I15: [Date] | J15: 0 | M15: Date | N15: 0
B16: Other | C16: 600 | H16: Gas | I16: [Date] | J16: 0 | M16: Date | N16: 100
H17: Cell phone | I17: [Date] | J17: 0
H18: Groceries | I18: [Date] | J18: 0
H19: Auto expenses | I19: [Date] | J19: 0
H20: Investments | I20: [Date] | J20: 0
H21: Credit cards | I21: [Date] | J21: 0
B22: Monthly GYM expenses | H22: Personal care | I22: [Date] | J22: 0
B23: ITEM | C23: AMOUNT | H23: Food | I23: [Date] | J23: 0
B24: Banana | H24: Miscellaneous | I24: [Date] | J24: 0
B25: Peanut butter
B26: Honey | C26: 0
B27: Oats | C27: 100
B28: Dates
B29: Chiceken / Panner
B30: Whey protien
B31: Creatin
B32: Nuts

Sheet sep
B1: Personal budget
B2: Percentage of income spent | C2: Summary
C3: TOTAL MONTHLY INCOME
C4: =SUM(MonthlyIncome558[[#All],[AMOUNT]]) -> 4000
C5: TOTAL MONTHLY EXPENSES
C6: =SUM(MonthlyExpenses659[AMOUNT])+SUM(Table6961[AMOUNT])+SUM(Savings3860[AMOUNT]) -> 800
C7: TOTAL MONTHLY SAVINGS
C8: =SUM(Savings3860[AMOUNT]) -> 200
C9: CASH BALANCE
C10: =C4-C6 -> 3200
B12: Monthly income | H12: Monthly expenses | M12: Monthly savings
B13: ITEM | C13: AMOUNT | H13: ITEM | I13: DUE DATE | J13: AMOUNT | M13: DATE | N13: AMOUNT
B14: Income source 1 | C14: 0 | H14: Rent/mortgage | I14: 45658 | J14: 0 | M14: Date | N14: 0
B15: Income source 2 | C15: 2000 | H15: Electric | I15: [Date] | J15: 0 | M15: Date | N15: 200
B16: Other | C16: 2000 | H16: Gas | I16: [Date] | J16: 0 | M16: Date | N16: 0
H17: Cell phone | I17: [Date] | J17: 0
H18: Groceries | I18: [Date] | J18: 0
H19: Auto expenses | I19: [Date] | J19: 0
H20: Investments | I20: [Date] | J20: 500
H21: Credit cards | I21: [Date] | J21: 0
B22: Monthly GYM expenses | H22: Personal care | I22: [Date] | J22: 0
B23: ITEM | C23: AMOUNT | H23: Food | I23: [Date] | J23: 0
B24: Banana | H24: Miscellaneous | I24: [Date] | J24: 0
B25: Peanut butter | J25: 0
B26: Honey | C26: 0 | J26: 0
B27: Oats | C27: 100
B28: Dates
B29: Chiceken / Panner
B30: Whey protien
B31: Creatin
B32: Nuts

Sheet oct
B1: Personal budget
B2: Percentage of income spent | C2: Summary
C3: TOTAL MONTHLY INCOME
C4: =SUM(MonthlyIncome55862[[#All],[AMOUNT]]) -> 400
C5: TOTAL MONTHLY EXPENSES
C6: =SUM(MonthlyExpenses65963[AMOUNT])+SUM(Table696165[AMOUNT])+SUM(Savings386064[AMOUNT]) -> 200
C7: TOTAL MONTHLY SAVINGS
C8: =SUM(Savings386064[AMOUNT]) -> 100
C9: CASH BALANCE
C10: =C4-C6 -> 200
B12: Monthly income | H12: Monthly expenses | M12: Monthly savings
B13: ITEM | C13: AMOUNT | H13: ITEM | I13: DUE DATE | J13: AMOUNT | M13: DATE | N13: AMOUNT
B14: Income source 1 | C14: 0 | H14: Rent/mortgage | I14: 45658 | J14: 0 | M14: Date | N14: 0
B15: Income source 2 | C15: 0 | H15: Electric | I15: [Date] | J15: 0 | M15: Date | N15: 0
B16: Other | C16: 400 | H16: Gas | I16: [Date] | J16: 0 | M16: Date | N16: 100
H17: Cell phone | I17: [Date] | J17: 0
H18: Groceries | I18: [Date] | J18: 0
H19: Auto expenses | I19: [Date] | J19: 0
H20: Investments | I20: [Date] | J20: 0
H21: Credit cards | I21: [Date] | J21: 0
B22: Monthly GYM expenses | H22: Personal care | I22: [Date] | J22: 0
B23: ITEM | C23: AMOUNT | H23: Food | I23: [Date] | J23: 0
B24: Banana | H24: Miscellaneous | I24: [Date] | J24: 0
B25: Peanut butter | J25: 0
B26: Honey | C26: 0
B27: Oats | C27: 100
B28: Dates
B29: Chiceken / Panner
B30: Whey protien
B31: Creatin
B32: Nuts

Sheet nov
B1: Personal budget
B2: Percentage of income spent | C2: Summary
C3: TOTAL MONTHLY INCOME
C4: =SUM(MonthlyIncome55866[[#All],[AMOUNT]]) -> 3000
C5: TOTAL MONTHLY EXPENSES
C6: =SUM(MonthlyExpenses65967[AMOUNT])+SUM(Table696169[AMOUNT])+SUM(Savings386068[AMOUNT]) -> 700
C7: TOTAL MONTHLY SAVINGS
C8: =SUM(Savings386068[AMOUNT]) -> 100
C9: CASH BALANCE
C10: =C4-C6 -> 2300
B12: Monthly income | H12: Monthly expenses | M12: Monthly savings
B13: ITEM | C13: AMOUNT | H13: ITEM | I13: DUE DATE | J13: AMOUNT | M13: DATE | N13: AMOUNT
B14: Income source 1 | C14: 400 | H14: Rent/mortgage | I14: 45658 | J14: 0 | M14: Date | N14: 0
B15: Income source 2 | C15: 2000 | H15: Electric | I15: [Date] | J15: 0 | M15: Date | N15: 0
B16: Other | C16: 600 | H16: Gas | I16: [Date] | J16: 0 | M16: Date | N16: 100
H17: Cell phone | I17: [Date] | J17: 500
H18: Groceries | I18: [Date] | J18: 0
H19: Auto expenses | I19: [Date] | J19: 0
H20: Investments | I20: [Date] | J20: 0
H21: Credit cards | I21: [Date] | J21: 0
B22: Monthly GYM expenses | H22: Personal care | I22: [Date] | J22: 0
B23: ITEM | C23: AMOUNT | H23: Food | I23: [Date] | J23: 0
B24: Banana | H24: Miscellaneous | I24: [Date] | J24: 0
B25: Peanut butter
B26: Honey | C26: 0
B27: Oats | C27: 100
B28: Dates
B29: Chiceken / Panner
B30: Whey protien
B31: Creatin
B32: Nuts

Sheet dec
B1: Personal budget
B2: Percentage of income spent | C2: Summary
C3: TOTAL MONTHLY INCOME
C4: =SUM(MonthlyIncome55870[[#All],[AMOUNT]]) -> 2900
C5: TOTAL MONTHLY EXPENSES
C6: =SUM(MonthlyExpenses65971[AMOUNT])+SUM(Table696173[AMOUNT])+SUM(Savings386072[AMOUNT]) -> 800
C7: TOTAL MONTHLY SAVINGS
C8: =SUM(Savings386072[AMOUNT]) -> 200
C9: CASH BALANCE
C10: =C4-C6 -> 2100
B12: Monthly income | H12: Monthly expenses | M12: Monthly savings
B13: ITEM | C13: AMOUNT | H13: ITEM | I13: DUE DATE | J13: AMOUNT | M13: DATE | N13: AMOUNT
B14: Income source 1 | C14: 400 | H14: Rent/mortgage | I14: 45658 | J14: 0 | M14: Date | N14: 0
B15: Income source 2 | C15: 2000 | H15: Electric | I15: [Date] | J15: 0 | M15: Date | N15: 200
B16: Other | C16: 500 | H16: Gas | I16: [Date] | J16: 0 | M16: Date | N16: 0
H17: Cell phone | I17: [Date] | J17: 0
H18: Groceries | I18: [Date] | J18: 0
H19: Auto expenses | I19: [Date] | J19: 0
H20: Investments | I20: [Date] | J20: 500
H21: Credit cards | I21: [Date] | J21: 0
B22: Monthly GYM expenses | H22: Personal care | I22: [Date] | J22: 0
B23: ITEM | C23: AMOUNT | H23: Food | I23: [Date] | J23: 0
B24: Banana | H24: Miscellaneous | I24: [Date] | J24: 0
B25: Peanut butter
B26: Honey | C26: 0
B27: Oats | C27: 100
B28: Dates
B29: Chiceken / Panner
B30: Whey protien
B31: Creatin
B32: Nuts

Sheet data
B1: jan | D1: feb | F1: mar | H1: april | J1: may | L1: june | N1: july | P1: aug | R1: sept | T1: oct | V1: nov | X1: dec
B2: =MIN(1,1-B3) -> 0.8 | D2: =MIN(1,1-D3) -> 0.8 | F2: =MIN(1,1-F3) -> 0.77272727 | H2: =MIN(1,1-H3) -> 0.9047619 | J2: =MIN(1,1-J3) -> 0.8 | L2: =MIN(1,1-L3) -> 0.73333333 | N2: =MIN(1,1-N3) -> 0.90625 | P2: =MIN(1,1-P3) -> 0.93333333 | R2: =MIN(1,1-R3) -> 0.8 | T2: =MIN(1,1-T3) -> 0.5 | V2: =MIN(1,1-V3) -> 0.76666667 | X2: =MIN(1,1-X3) -> 0.72413793
B3: =MIN(jan!C6/jan!C4,1) -> 0.2 | D3: =MIN(feb!C6/feb!C4,1) -> 0.2 | F3: =MIN(mar!C6/mar!C4,1) -> 0.22727273 | H3: =MIN(apr!C6/apr!C4,1) -> 0.095238095 | J3: =MIN(may!C6/may!C4,1) -> 0.2 | L3: =MIN(jun!C6/jun!C4,1) -> 0.26666667 | N3: =MIN(jul!C6/jul!C4,1) -> 0.09375 | P3: =MIN(aug!C6/aug!C4,1) -> 0.066666667 | R3: =MIN(sep!C6/sep!C4,1) -> 0.2 | T3: =MIN(oct!C6/oct!C4,1) -> 0.5 | V3: =MIN(nov!C6/nov!C4,1) -> 0.23333333 | X3: =MIN(dec!C6/dec!C4,1) -> 0.27586207
B4: =(jan!C6/jan!C4)>1 -> FALSE | D4: =(feb!C6/feb!C4)>1 -> FALSE | F4: =(mar!C6/mar!C4)>1 -> FALSE | H4: =(apr!C6/apr!C4)>1 -> FALSE | J4: =(may!C6/may!C4)>1 -> FALSE | L4: =(jun!C6/jun!C4)>1 -> FALSE | N4: =(jul!C6/jul!C4)>1 -> FALSE | P4: =(aug!C6/aug!C4)>1 -> FALSE | R4: =(sep!C6/sep!C4)>1 -> FALSE | T4: =(oct!C6/oct!C4)>1 -> FALSE | V4: =(nov!C6/nov!C4)>1 -> FALSE | X4: =(dec!C6/dec!C4)>1 -> FALSE
